[{"id":1,"name":"阿拉善左旗","normalizedName":"阿拉善左旗","province":"内蒙古","lng":103.398098,"lat":40.110314},{"id":3,"name":"阿勒泰市","normalizedName":"阿勒泰","province":"新疆","lng":88.389609,"lat":47.036396},{"id":4,"name":"阿图什市","normalizedName":"阿图什","province":"新疆","lng":75.96226,"lat":39.625089},{"id":3,"name":"阿瓦提县","normalizedName":"阿瓦提县","province":"新疆","lng":81.241823,"lat":40.989222},{"id":3,"name":"安康市","normalizedName":"安康","province":"山西","lng":108.922219,"lat":32.872674},{"id":2,"name":"安庆市","normalizedName":"安庆","province":"安徽","lng":116.631415,"lat":30.602554},{"id":4,"name":"安顺市","normalizedName":"安顺","province":"贵州","lng":105.954728,"lat":26.0047},{"id":3,"name":"安阳市","normalizedName":"安阳","province":"河南","lng":114.296017,"lat":35.85043},{"id":1,"name":"鞍山市","normalizedName":"鞍山","province":"辽宁","lng":122.88414,"lat":40.797335},{"id":"chongqing-巴南区","name":"巴南区","normalizedName":"巴南区","province":"重庆","lng":106.767223,"lat":29.377102},{"id":4,"name":"巴中县","normalizedName":"巴中县","province":"四川","lng":107.015975,"lat":31.994212},{"id":1,"name":"白城市","normalizedName":"白城","province":"吉林","lng":122.940354,"lat":45.422723},{"id":3,"name":"百色市","normalizedName":"百色","province":"广西","lng":106.25605,"lat":24.007662},{"id":4,"name":"蚌埠市","normalizedName":"蚌埠","province":"安徽","lng":117.340726,"lat":33.11398},{"id":4,"name":"包头市","normalizedName":"包头","province":"内蒙古","lng":110.286827,"lat":41.323776},{"id":"tianjin-宝坻县","name":"宝坻县","normalizedName":"宝坻县","province":"天津","lng":117.441187,"lat":39.623954},{"id":3,"name":"宝鸡市","normalizedName":"宝鸡","province":"山西","lng":107.156027,"lat":34.346271},{"id":1,"name":"保定市","normalizedName":"保定","province":"河北","lng":115.141575,"lat":39.060942},{"id":3,"name":"保山市","normalizedName":"保山","province":"云南","lng":99.028421,"lat":25.010939},{"id":"chongqing-北碚区","name":"北碚区","normalizedName":"北碚区","province":"重庆","lng":106.472738,"lat":29.857544},{"id":1,"name":"北海市","normalizedName":"北海","province":"广西","lng":109.336067,"lat":21.672048},{"id":2,"name":"北海市","normalizedName":"北海","province":"广西","lng":109.168853,"lat":21.49423},{"id":4,"name":"本溪市","normalizedName":"本溪","province":"辽宁","lng":124.023401,"lat":41.182996},{"id":1,"name":"毕节市","normalizedName":"毕节","province":"贵州","lng":105.405838,"lat":27.101729},{"id":"chongqing-璧山县","name":"璧山县","normalizedName":"璧山县","province":"重庆","lng":106.193777,"lat":29.5859},{"id":1,"name":"滨州市","normalizedName":"滨州","province":"山东","lng":117.867685,"lat":37.564409},{"id":3,"name":"亳州市","normalizedName":"亳州","province":"安徽","lng":116.133652,"lat":33.465842},{"id":3,"name":"博乐市","normalizedName":"博乐","province":"新疆","lng":81.898187,"lat":44.719569},{"id":2,"name":"沧州市","normalizedName":"沧州","province":"河北","lng":116.748978,"lat":38.272135},{"id":1,"name":"昌都","normalizedName":"昌都","province":"西藏","lng":96.772047,"lat":30.481408},{"id":"beijing-昌平","name":"昌平","normalizedName":"昌平","province":"北京","lng":116.176919,"lat":40.202722},{"id":3,"name":"常德市","normalizedName":"常德","province":"湖南","lng":111.400177,"lat":29.229052},{"id":1,"name":"常州市","normalizedName":"常州","province":"江苏","lng":119.651155,"lat":31.618971},{"id":1,"name":"巢湖市","normalizedName":"巢湖","province":"安徽","lng":117.795443,"lat":31.503215},{"id":3,"name":"朝阳市","normalizedName":"朝阳","province":"辽宁","lng":119.975342,"lat":41.455954},{"id":3,"name":"潮州市","normalizedName":"潮州","province":"广东","lng":116.771557,"lat":23.774165},{"id":4,"name":"郴州市","normalizedName":"郴州","province":"湖南","lng":113.122539,"lat":25.762028},{"id":3,"name":"成都市","normalizedName":"成都","province":"四川","lng":103.880171,"lat":30.686987},{"id":4,"name":"成县","normalizedName":"成县","province":"甘肃","lng":105.302044,"lat":33.706714},{"id":4,"name":"承德市","normalizedName":"承德","province":"河北","lng":117.617033,"lat":41.293716},{"id":2,"name":"赤峰市","normalizedName":"赤峰","province":"内蒙古","lng":118.874126,"lat":43.058666},{"id":"shanghai-崇明县","name":"崇明县","normalizedName":"崇明县","province":"上海","lng":121.519277,"lat":31.640449},{"id":"shanghai-崇明县","name":"崇明县","normalizedName":"崇明县","province":"上海","lng":121.182937,"lat":31.778884},{"id":"shanghai-崇明县","name":"崇明县","normalizedName":"崇明县","province":"上海","lng":121.214316,"lat":31.749362},{"id":"shanghai-崇明县","name":"崇明县","normalizedName":"崇明县","province":"上海","lng":121.43859,"lat":31.763609},{"id":"shanghai-崇明县","name":"崇明县","normalizedName":"崇明县","province":"上海","lng":121.241446,"lat":31.73534},{"id":"shanghai-崇明县","name":"崇明县","normalizedName":"崇明县","province":"上海","lng":121.359663,"lat":31.609913},{"id":3,"name":"滁州市","normalizedName":"滁州","province":"安徽","lng":117.971859,"lat":32.547374},{"id":2,"name":"楚雄市","normalizedName":"楚雄","province":"云南","lng":101.587071,"lat":25.340635},{"id":2,"name":"达川市","normalizedName":"达川","province":"四川","lng":107.679724,"lat":31.364903},{"id":"chongqing-大渡口区","name":"大渡口区","normalizedName":"大渡口区","province":"重庆","lng":106.474809,"lat":29.428384},{"id":2,"name":"大连市","normalizedName":"大连","province":"辽宁","lng":122.191664,"lat":39.423777},{"id":3,"name":"大庆市","normalizedName":"大庆","province":"黑龙江","lng":124.907749,"lat":46.356321},{"id":4,"name":"大同市","normalizedName":"大同","province":"陕西","lng":113.698751,"lat":39.941997},{"id":"beijing-大兴","name":"大兴","normalizedName":"大兴","province":"北京","lng":116.445245,"lat":39.654304},{"id":2,"name":"大庸市","normalizedName":"大庸","province":"湖南","lng":110.467015,"lat":29.353299},{"id":"chongqing-大足县","name":"大足县","normalizedName":"大足县","province":"重庆","lng":105.722106,"lat":29.639841},{"id":3,"name":"岱山县","normalizedName":"岱山县","province":"浙江","lng":122.151026,"lat":30.278068},{"id":3,"name":"丹东市","normalizedName":"丹东","province":"辽宁","lng":124.352092,"lat":40.460733},{"id":4,"name":"德阳市","normalizedName":"德阳","province":"四川","lng":104.498845,"lat":31.094903},{"id":4,"name":"德州市","normalizedName":"德州","province":"山东","lng":116.66804,"lat":37.253309},{"id":"chongqing-垫江县","name":"垫江县","normalizedName":"垫江县","province":"重庆","lng":107.436687,"lat":30.239691},{"id":1,"name":"定西县","normalizedName":"定西县","province":"甘肃","lng":104.443023,"lat":35.093925},{"id":3,"name":"东莞市","normalizedName":"东莞","province":"广东","lng":113.883688,"lat":22.903303},{"id":3,"name":"东胜市","normalizedName":"东胜","province":"内蒙古","lng":108.894629,"lat":39.57494},{"id":2,"name":"东营市","normalizedName":"东营","province":"山东","lng":118.620822,"lat":37.705282},{"id":2,"name":"都匀市","normalizedName":"都匀","province":"贵州","lng":107.236719,"lat":26.187829},{"id":3,"name":"鄂州市","normalizedName":"鄂州","province":"湖北","lng":114.752251,"lat":30.321156},{"id":4,"name":"恩施市","normalizedName":"恩施","province":"湖北","lng":109.522671,"lat":30.152136},{"id":1,"name":"防城港市","normalizedName":"防城港","province":"广西","lng":108.138501,"lat":21.762263},{"id":"beijing-房山","name":"房山","normalizedName":"房山","province":"北京","lng":115.859083,"lat":39.711191},{"id":"chongqing-丰都县","name":"丰都县","normalizedName":"丰都县","province":"重庆","lng":107.848366,"lat":29.888721},{"id":2,"name":"凤山县","normalizedName":"凤山县","province":"台湾","lng":120.578894,"lat":22.977915},{"id":"chongqing-奉节县","name":"奉节县","normalizedName":"奉节县","province":"重庆","lng":109.320079,"lat":30.894848},{"id":"shanghai-奉贤县","name":"奉贤县","normalizedName":"奉贤县","province":"上海","lng":121.511394,"lat":30.924508},{"id":1,"name":"佛山市","normalizedName":"佛山","province":"广东","lng":112.86415,"lat":22.988582},{"id":1,"name":"扶顺市","normalizedName":"扶顺","province":"辽宁","lng":124.586245,"lat":41.816713},{"id":2,"name":"扶余市","normalizedName":"扶余","province":"吉林","lng":124.571859,"lat":44.787294},{"id":"chongqing-涪陵区","name":"涪陵区","normalizedName":"涪陵区","province":"重庆","lng":107.328537,"lat":29.658898},{"id":2,"name":"福州市","normalizedName":"福州","province":"福建","lng":119.379104,"lat":25.972686},{"id":1,"name":"阜新市","normalizedName":"阜新","province":"辽宁","lng":121.961301,"lat":42.282151},{"id":1,"name":"阜阳市","normalizedName":"阜阳","province":"安徽","lng":115.667462,"lat":32.847289},{"id":1,"name":"噶尔县","normalizedName":"噶尔县","province":"西藏","lng":82.769119,"lat":32.074349},{"id":1,"name":"赣州市","normalizedName":"赣州","province":"江西","lng":115.153321,"lat":25.606435},{"id":4,"name":"高雄市","normalizedName":"高雄","province":"台湾","lng":120.296936,"lat":22.644214},{"id":4,"name":"格尔木市","normalizedName":"格尔木","province":"青海","lng":91.404606,"lat":34.010902},{"id":1,"name":"个旧市","normalizedName":"个旧","province":"云南","lng":103.071875,"lat":23.418949},{"id":3,"name":"共和县","normalizedName":"共和县","province":"青海","lng":100.328436,"lat":35.914376},{"id":1,"name":"固原县","normalizedName":"固原县","province":"宁夏","lng":105.936702,"lat":36.085972},{"id":3,"name":"广元市","normalizedName":"广元","province":"四川","lng":105.727315,"lat":32.251962},{"id":4,"name":"广州市","normalizedName":"广州","province":"广东","lng":113.546481,"lat":23.277187},{"id":4,"name":"贵池市","normalizedName":"贵池","province":"安徽","lng":117.338188,"lat":30.250281},{"id":4,"name":"贵港市","normalizedName":"贵港","province":"广西","lng":110.009503,"lat":23.34716},{"id":3,"name":"贵阳市","normalizedName":"贵阳","province":"贵州","lng":106.709175,"lat":26.825525},{"id":1,"name":"桂林市","normalizedName":"桂林","province":"广西","lng":110.487922,"lat":25.325967},{"id":1,"name":"哈尔滨市","normalizedName":"哈尔滨","province":"黑龙江","lng":128.081517,"lat":45.558824},{"id":3,"name":"哈密市","normalizedName":"哈密","province":"新疆","lng":93.21929,"lat":43.146928},{"id":2,"name":"海丰县","normalizedName":"海丰县","province":"广东","lng":115.495097,"lat":22.908445},{"id":1,"name":"海口市","normalizedName":"海口","province":"海南","lng":109.859919,"lat":19.137264},{"id":3,"name":"海拉尔市","normalizedName":"海拉尔","province":"内蒙古","lng":121.1392,"lat":50.024113},{"id":4,"name":"邯郸市","normalizedName":"邯郸","province":"河北","lng":114.472247,"lat":36.539762},{"id":1,"name":"汉中市","normalizedName":"汉中","province":"山西","lng":107.04318,"lat":33.09567},{"id":1,"name":"杭州市","normalizedName":"杭州","province":"浙江","lng":119.587609,"lat":29.917454},{"id":"chongqing-合川市","name":"合川市","normalizedName":"合川","province":"重庆","lng":106.284119,"lat":30.124019},{"id":4,"name":"合肥市","normalizedName":"合肥","province":"安徽","lng":117.193533,"lat":32.017657},{"id":2,"name":"合山市","normalizedName":"合山","province":"广西","lng":109.363173,"lat":24.606993},{"id":4,"name":"和田市","normalizedName":"和田","province":"新疆","lng":80.742958,"lat":37.088163},{"id":4,"name":"河池市","normalizedName":"河池","province":"广西","lng":107.856424,"lat":24.712103},{"id":3,"name":"河源市","normalizedName":"河源","province":"广东","lng":114.922026,"lat":24.137821},{"id":1,"name":"菏泽市","normalizedName":"菏泽","province":"山东","lng":115.746567,"lat":35.054281},{"id":4,"name":"贺州市","normalizedName":"贺州","province":"广西","lng":111.348385,"lat":24.331445},{"id":1,"name":"鹤壁市","normalizedName":"鹤壁","province":"河南","lng":114.284877,"lat":35.757338},{"id":4,"name":"鹤岗市","normalizedName":"鹤岗","province":"黑龙江","lng":130.764075,"lat":47.644178},{"id":1,"name":"黑河市","normalizedName":"黑河","province":"黑龙江","lng":126.971759,"lat":49.101585},{"id":3,"name":"衡水市","normalizedName":"衡水","province":"河北","lng":115.798645,"lat":37.762974},{"id":1,"name":"衡阳市","normalizedName":"衡阳","province":"湖南","lng":112.445161,"lat":26.797554},{"id":1,"name":"呼和浩特市","normalizedName":"呼和浩特","province":"内蒙古","lng":111.371542,"lat":40.671312},{"id":4,"name":"湖州市","normalizedName":"湖州","province":"浙江","lng":119.890332,"lat":30.765815},{"id":1,"name":"葫芦岛市","normalizedName":"葫芦岛","province":"辽宁","lng":120.262059,"lat":40.621225},{"id":4,"name":"华蓥市","normalizedName":"华蓥","province":"四川","lng":106.650464,"lat":30.419845},{"id":4,"name":"怀化市","normalizedName":"怀化","province":"湖南","lng":110.072135,"lat":27.520806},{"id":"beijing-怀柔","name":"怀柔","normalizedName":"怀柔","province":"北京","lng":116.578754,"lat":40.620508},{"id":1,"name":"淮北市","normalizedName":"淮北","province":"安徽","lng":116.785333,"lat":33.82945},{"id":2,"name":"淮南市","normalizedName":"淮南","province":"安徽","lng":116.725064,"lat":32.779247},{"id":4,"name":"淮阴市","normalizedName":"淮阴","province":"江苏","lng":118.894074,"lat":33.282947},{"id":2,"name":"桓仁满族自治县","normalizedName":"桓仁满族自治县","province":"辽宁","lng":125.259134,"lat":41.237307},{"id":2,"name":"黄山市","normalizedName":"黄山","province":"安徽","lng":118.083663,"lat":29.957111},{"id":1,"name":"黄石市","normalizedName":"黄石","province":"湖北","lng":114.96201,"lat":29.947042},{"id":1,"name":"惠州市","normalizedName":"惠州","province":"广东","lng":114.569932,"lat":23.130082},{"id":3,"name":"浑江市","normalizedName":"浑江","province":"吉林","lng":127.230064,"lat":42.001277},{"id":1,"name":"鸡西市","normalizedName":"鸡西","province":"黑龙江","lng":132.271883,"lat":45.690515},{"id":3,"name":"基隆市","normalizedName":"基隆","province":"台湾","lng":121.686741,"lat":25.115607},{"id":3,"name":"吉安市","normalizedName":"吉安","province":"江西","lng":114.810304,"lat":26.914821},{"id":2,"name":"吉林市","normalizedName":"吉林","province":"吉林","lng":126.793418,"lat":43.574088},{"id":3,"name":"吉首市","normalizedName":"吉首","province":"湖南","lng":109.726355,"lat":28.706361},{"id":2,"name":"集宁市","normalizedName":"集宁","province":"内蒙古","lng":112.62934,"lat":41.738972},{"id":2,"name":"济南市","normalizedName":"济南","province":"山东","lng":117.02397,"lat":36.704926},{"id":3,"name":"济宁市","normalizedName":"济宁","province":"山东","lng":116.727144,"lat":35.328585},{"id":3,"name":"济源市","normalizedName":"济源","province":"河南","lng":112.372696,"lat":35.113221},{"id":"tianjin-蓟县","name":"蓟县","normalizedName":"蓟县","province":"天津","lng":117.453169,"lat":40.027809},{"id":2,"name":"佳木斯市","normalizedName":"佳木斯","province":"黑龙江","lng":131.883887,"lat":47.13024},{"id":"shanghai-嘉定区","name":"嘉定区","normalizedName":"嘉定区","province":"上海","lng":121.255194,"lat":31.351856},{"id":3,"name":"嘉兴市","normalizedName":"嘉兴","province":"浙江","lng":120.789404,"lat":30.670622},{"id":4,"name":"嘉义县","normalizedName":"嘉义县","province":"台湾","lng":120.533743,"lat":23.451474},{"id":4,"name":"嘉峪关市","normalizedName":"嘉峪关","province":"甘肃","lng":98.199919,"lat":39.759645},{"id":"chongqing-江北区","name":"江北区","normalizedName":"江北区","province":"重庆","lng":106.681889,"lat":29.610939},{"id":"chongqing-江津市","name":"江津市","normalizedName":"江津","province":"重庆","lng":106.260599,"lat":29.015032},{"id":3,"name":"江门市","normalizedName":"江门","province":"广东","lng":112.684489,"lat":22.244535},{"id":2,"name":"焦作市","normalizedName":"焦作","province":"河南","lng":113.096426,"lat":35.170266},{"id":1,"name":"揭阳县","normalizedName":"揭阳县","province":"广东","lng":116.173271,"lat":23.295318},{"id":4,"name":"金昌市","normalizedName":"金昌","province":"甘肃","lng":102.010896,"lat":38.418733},{"id":3,"name":"金华市","normalizedName":"金华","province":"浙江","lng":119.797566,"lat":29.092318},{"id":2,"name":"金门县","normalizedName":"金门县","province":"福建","lng":118.3927,"lat":24.438954},{"id":"shanghai-金山区","name":"金山区","normalizedName":"金山区","province":"上海","lng":121.164239,"lat":30.857952},{"id":"shanghai-金山区","name":"金山区","normalizedName":"金山区","province":"上海","lng":121.417889,"lat":30.69481},{"id":2,"name":"锦州市","normalizedName":"锦州","province":"辽宁","lng":121.549212,"lat":41.376039},{"id":1,"name":"晋城市","normalizedName":"晋城","province":"陕西","lng":112.732478,"lat":35.68938},{"id":3,"name":"荆门市","normalizedName":"荆门","province":"湖北","lng":112.595999,"lat":31.057478},{"id":3,"name":"景德镇市","normalizedName":"景德镇","province":"江西","lng":117.258257,"lat":29.302454},{"id":2,"name":"景洪市","normalizedName":"景洪","province":"云南","lng":101.034357,"lat":21.817487},{"id":"tianjin-静海县","name":"静海县","normalizedName":"静海县","province":"天津","lng":116.965337,"lat":38.82967},{"id":3,"name":"九江市","normalizedName":"九江","province":"江西","lng":115.553004,"lat":29.306703},{"id":"chongqing-九龙坡区","name":"九龙坡区","normalizedName":"九龙坡区","province":"重庆","lng":106.361155,"lat":29.408155},{"id":2,"name":"酒泉市","normalizedName":"酒泉","province":"甘肃","lng":96.804729,"lat":39.93299},{"id":2,"name":"喀什市","normalizedName":"喀什","province":"新疆","lng":76.840846,"lat":38.090557},{"id":3,"name":"开封市","normalizedName":"开封","province":"河南","lng":114.576981,"lat":34.624873},{"id":"chongqing-开江县","name":"开江县","normalizedName":"开江县","province":"重庆","lng":107.882305,"lat":31.046099},{"id":"chongqing-开县","name":"开县","normalizedName":"开县","province":"重庆","lng":108.405715,"lat":31.286672},{"id":3,"name":"凯里市","normalizedName":"凯里","province":"贵州","lng":108.501818,"lat":26.53901},{"id":4,"name":"康定县","normalizedName":"康定县","province":"四川","lng":100.164556,"lat":30.638964},{"id":1,"name":"克拉玛依市","normalizedName":"克拉玛依","province":"新疆","lng":85.205199,"lat":45.451708},{"id":1,"name":"库尔勒市","normalizedName":"库尔勒","province":"新疆","lng":87.296512,"lat":39.985058},{"id":2,"name":"奎屯市","normalizedName":"奎屯","province":"新疆","lng":84.969254,"lat":44.434737},{"id":3,"name":"昆明市","normalizedName":"昆明","province":"云南","lng":102.932465,"lat":25.328859},{"id":4,"name":"拉萨市","normalizedName":"拉萨","province":"西藏","lng":91.403288,"lat":29.943461},{"id":3,"name":"莱芜市","normalizedName":"莱芜","province":"山东","lng":117.610438,"lat":36.269974},{"id":3,"name":"兰州市","normalizedName":"兰州","province":"甘肃","lng":103.635063,"lat":36.287462},{"id":3,"name":"廊坊市","normalizedName":"廊坊","province":"河北","lng":116.548593,"lat":39.147341},{"id":3,"name":"乐山市","normalizedName":"乐山","province":"四川","lng":103.573622,"lat":29.200791},{"id":1,"name":"离石县","normalizedName":"离石县","province":"陕西","lng":111.331504,"lat":37.615452},{"id":3,"name":"丽江纳西族自治县","normalizedName":"丽江纳西族自治县","province":"云南","lng":100.387376,"lat":26.941516},{"id":2,"name":"丽水市","normalizedName":"丽水","province":"浙江","lng":119.554549,"lat":28.234726},{"id":3,"name":"连云港市","normalizedName":"连云港","province":"江苏","lng":119.148327,"lat":34.553538},{"id":1,"name":"莲花县","normalizedName":"莲花县","province":"江西","lng":113.931549,"lat":27.211455},{"id":4,"name":"莲花县","normalizedName":"莲花县","province":"台湾","lng":121.368786,"lat":23.776984},{"id":"chongqing-梁平县","name":"梁平县","normalizedName":"梁平县","province":"重庆","lng":107.726515,"lat":30.647845},{"id":2,"name":"辽阳市","normalizedName":"辽阳","province":"辽宁","lng":123.155805,"lat":41.173028},{"id":3,"name":"辽源市","normalizedName":"辽源","province":"吉林","lng":125.32765,"lat":42.825561},{"id":1,"name":"聊城市","normalizedName":"聊城","province":"山东","lng":115.827613,"lat":36.430271},{"id":3,"name":"林芝县","normalizedName":"林芝县","province":"西藏","lng":95.692635,"lat":29.178985},{"id":4,"name":"临沧县","normalizedName":"临沧县","province":"云南","lng":99.672375,"lat":23.977698},{"id":2,"name":"临川市","normalizedName":"临川","province":"江西","lng":116.424258,"lat":27.501121},{"id":4,"name":"临汾市","normalizedName":"临汾","province":"陕西","lng":111.2991,"lat":36.231238},{"id":2,"name":"临河市","normalizedName":"临河","province":"内蒙古","lng":107.837531,"lat":41.244709},{"id":2,"name":"临夏市","normalizedName":"临夏","province":"甘肃","lng":103.379101,"lat":35.724705},{"id":2,"name":"临沂市","normalizedName":"临沂","province":"山东","lng":118.374091,"lat":35.327673},{"id":1,"name":"柳州市","normalizedName":"柳州","province":"广西","lng":109.267984,"lat":24.421154},{"id":3,"name":"六安市","normalizedName":"六安","province":"安徽","lng":116.357504,"lat":31.786649},{"id":2,"name":"六盘水市","normalizedName":"六盘水","province":"贵州","lng":104.985006,"lat":26.220098},{"id":2,"name":"龙岩市","normalizedName":"龙岩","province":"福建","lng":116.775912,"lat":25.347845},{"id":2,"name":"娄底市","normalizedName":"娄底","province":"湖南","lng":111.660313,"lat":27.701745},{"id":2,"name":"泸州市","normalizedName":"泸州","province":"四川","lng":105.724572,"lat":28.375474},{"id":4,"name":"潞西市","normalizedName":"潞西","province":"云南","lng":98.0679,"lat":24.582185},{"id":4,"name":"洛阳市","normalizedName":"洛阳","province":"河南","lng":112.03108,"lat":34.314166},{"id":3,"name":"漯河市","normalizedName":"漯河","province":"河南","lng":113.761884,"lat":33.595656},{"id":4,"name":"麻城市","normalizedName":"麻城","province":"湖北","lng":115.273911,"lat":30.762369},{"id":2,"name":"马鞍山市","normalizedName":"马鞍山","province":"安徽","lng":118.589913,"lat":31.559586},{"id":1,"name":"马尔康县","normalizedName":"马尔康县","province":"四川","lng":102.715958,"lat":32.400675},{"id":1,"name":"马山县","normalizedName":"马山县","province":"广西","lng":108.63367,"lat":23.326252},{"id":2,"name":"玛纳斯县","normalizedName":"玛纳斯县","province":"新疆","lng":88.538809,"lat":44.206025},{"id":2,"name":"玛沁县","normalizedName":"玛沁县","province":"青海","lng":99.390687,"lat":34.144726},{"id":1,"name":"茂名市","normalizedName":"茂名","province":"广东","lng":110.932544,"lat":22.053072},{"id":4,"name":"梅州市","normalizedName":"梅州","province":"广东","lng":115.964398,"lat":24.132814},{"id":"beijing-门头沟","name":"门头沟","normalizedName":"门头沟","province":"北京","lng":115.795752,"lat":40.014479},{"id":1,"name":"门源回族自治县","normalizedName":"门源回族自治县","province":"青海","lng":100.280214,"lat":37.651673},{"id":"beijing-密云","name":"密云","normalizedName":"密云","province":"北京","lng":117.016711,"lat":40.532782},{"id":2,"name":"绵阳市","normalizedName":"绵阳","province":"四川","lng":104.647288,"lat":31.893301},{"id":4,"name":"苗栗县","normalizedName":"苗栗县","province":"台湾","lng":120.905451,"lat":24.497683},{"id":"shanghai-闵行区","name":"闵行区","normalizedName":"闵行区","province":"上海","lng":121.432846,"lat":31.115384},{"id":3,"name":"牡丹江市","normalizedName":"牡丹江","province":"黑龙江","lng":129.846789,"lat":44.666655},{"id":4,"name":"牡丹江市","normalizedName":"牡丹江","province":"吉林","lng":129.328108,"lat":43.108981},{"id":2,"name":"那曲县","normalizedName":"那曲县","province":"西藏","lng":89.474449,"lat":32.294154},{"id":"chongqing-南岸区","name":"南岸区","normalizedName":"南岸区","province":"重庆","lng":106.650176,"lat":29.540942},{"id":4,"name":"南澳县","normalizedName":"南澳县","province":"广东","lng":117.074123,"lat":23.449664},{"id":4,"name":"南昌市","normalizedName":"南昌","province":"江西","lng":116.067484,"lat":28.774721},{"id":1,"name":"南充县","normalizedName":"南充县","province":"四川","lng":106.177713,"lat":31.224249},{"id":"chongqing-南川市","name":"南川市","normalizedName":"南川","province":"重庆","lng":107.141376,"lat":29.132684},{"id":"shanghai-南汇县","name":"南汇县","normalizedName":"南汇县","province":"上海","lng":121.658463,"lat":31.068311},{"id":4,"name":"南京市","normalizedName":"南京","province":"江苏","lng":118.819193,"lat":31.928971},{"id":4,"name":"南宁市","normalizedName":"南宁","province":"广西","lng":108.259621,"lat":22.929992},{"id":3,"name":"南平市","normalizedName":"南平","province":"福建","lng":118.17811,"lat":27.329821},{"id":1,"name":"南投县","normalizedName":"南投县","province":"台湾","lng":120.961749,"lat":23.872016},{"id":3,"name":"南阳市","normalizedName":"南阳","province":"河南","lng":112.390555,"lat":33.022852},{"id":4,"name":"内江市","normalizedName":"内江","province":"四川","lng":104.887372,"lat":29.643288},{"id":1,"name":"宁波市","normalizedName":"宁波","province":"浙江","lng":121.595486,"lat":29.562749},{"id":1,"name":"宁德市","normalizedName":"宁德","province":"福建","lng":119.665359,"lat":26.918468},{"id":"tianjin-宁河县","name":"宁河县","normalizedName":"宁河县","province":"天津","lng":117.709938,"lat":39.363914},{"id":4,"name":"怒江傈傈族自治州","normalizedName":"怒江傈傈族","province":"云南","lng":98.806611,"lat":26.982465},{"id":4,"name":"攀枝花市","normalizedName":"攀枝花","province":"四川","lng":101.770372,"lat":26.826098},{"id":3,"name":"盘锦市","normalizedName":"盘锦","province":"辽宁","lng":121.989045,"lat":41.003934},{"id":"chongqing-彭水苗族土家族自治县","name":"彭水苗族土家族自治县","normalizedName":"彭水苗族土家族自治县","province":"重庆","lng":108.271669,"lat":29.367465},{"id":4,"name":"平安县","normalizedName":"平安县","province":"青海","lng":102.334215,"lat":36.326488},{"id":2,"name":"平顶山市","normalizedName":"平顶山","province":"河南","lng":113.16026,"lat":33.676954},{"id":"beijing-平谷","name":"平谷","normalizedName":"平谷","province":"北京","lng":117.158028,"lat":40.205063},{"id":4,"name":"平凉市","normalizedName":"平凉","province":"甘肃","lng":105.549973,"lat":35.943584},{"id":4,"name":"平潭县","normalizedName":"平潭县","province":"福建","lng":119.766364,"lat":25.503409},{"id":2,"name":"凭祥市","normalizedName":"凭祥","province":"广西","lng":107.341919,"lat":22.568428},{"id":1,"name":"屏东县","normalizedName":"屏东县","province":"台湾","lng":120.710721,"lat":22.391404},{"id":4,"name":"萍乡市","normalizedName":"萍乡","province":"江西","lng":113.850617,"lat":27.638626},{"id":1,"name":"莆田市","normalizedName":"莆田","province":"福建","lng":118.990782,"lat":25.349586},{"id":2,"name":"濮阳市","normalizedName":"濮阳","province":"河南","lng":115.384169,"lat":35.853236},{"id":4,"name":"七台河市","normalizedName":"七台河","province":"黑龙江","lng":131.181553,"lat":45.959294},{"id":4,"name":"齐齐哈尔市","normalizedName":"齐齐哈尔","province":"黑龙江","lng":124.504044,"lat":47.557484},{"id":"chongqing-綦江县","name":"綦江县","normalizedName":"綦江县","province":"重庆","lng":106.678497,"lat":28.835916},{"id":2,"name":"潜江市","normalizedName":"潜江","province":"湖北","lng":112.741012,"lat":30.370377},{"id":"chongqing-黔江土家族苗族自治县","name":"黔江土家族苗族自治县","normalizedName":"黔江土家族苗族自治县","province":"重庆","lng":108.789863,"lat":31.870121},{"id":"chongqing-黔江土家族苗族自治县","name":"黔江土家族苗族自治县","normalizedName":"黔江土家族苗族自治县","province":"重庆","lng":108.708024,"lat":29.477696},{"id":3,"name":"钦州市","normalizedName":"钦州","province":"广西","lng":108.94632,"lat":22.047089},{"id":2,"name":"秦皇岛市","normalizedName":"秦皇岛","province":"河北","lng":119.161015,"lat":39.962999},{"id":1,"name":"青岛市","normalizedName":"青岛","province":"山东","lng":120.228944,"lat":36.269864},{"id":"shanghai-青浦县","name":"青浦县","normalizedName":"青浦县","province":"上海","lng":121.07504,"lat":31.103103},{"id":4,"name":"清河门区","normalizedName":"清河门区","province":"辽宁","lng":121.413202,"lat":41.721426},{"id":3,"name":"清远市","normalizedName":"清远","province":"广东","lng":112.768804,"lat":24.405625},{"id":4,"name":"曲靖市","normalizedName":"曲靖","province":"云南","lng":103.851522,"lat":25.676956},{"id":4,"name":"衢州市","normalizedName":"衢州","province":"浙江","lng":118.811878,"lat":28.943332},{"id":3,"name":"泉州市","normalizedName":"泉州","province":"福建","lng":118.454445,"lat":25.114476},{"id":1,"name":"仁寿县","normalizedName":"仁寿县","province":"四川","lng":103.652382,"lat":29.860991},{"id":3,"name":"日喀则市","normalizedName":"日喀则","province":"西藏","lng":86.043063,"lat":29.693027},{"id":4,"name":"日照市","normalizedName":"日照","province":"山东","lng":119.133349,"lat":35.513732},{"id":"chongqing-荣昌县","name":"荣昌县","normalizedName":"荣昌县","province":"重庆","lng":105.498473,"lat":29.469482},{"id":1,"name":"三门峡市","normalizedName":"三门峡","province":"河南","lng":111.154579,"lat":34.363724},{"id":4,"name":"三明市","normalizedName":"三明","province":"福建","lng":117.423563,"lat":26.260792},{"id":2,"name":"三亚市","normalizedName":"三亚","province":"海南","lng":109.48862,"lat":18.437996},{"id":"chongqing-沙坪坝区","name":"沙坪坝区","normalizedName":"沙坪坝区","province":"重庆","lng":106.40628,"lat":29.621055},{"id":1,"name":"沙市市","normalizedName":"沙市","province":"湖北","lng":112.536608,"lat":30.018601},{"id":3,"name":"沙湾县","normalizedName":"沙湾县","province":"新疆","lng":85.39837,"lat":44.215854},{"id":4,"name":"厦门市","normalizedName":"厦门","province":"福建","lng":118.121386,"lat":24.616283},{"id":2,"name":"汕头市","normalizedName":"汕头","province":"广东","lng":116.604393,"lat":23.338746},{"id":4,"name":"商丘市","normalizedName":"商丘","province":"河南","lng":115.75104,"lat":34.266764},{"id":4,"name":"商州市","normalizedName":"商州","province":"山西","lng":109.858777,"lat":33.695858},{"id":"shanghai-上海市","name":"上海市","normalizedName":"上海","province":"上海","lng":121.417512,"lat":31.353848},{"id":"shanghai-上海市","name":"上海市","normalizedName":"上海","province":"上海","lng":121.588676,"lat":31.44519},{"id":"shanghai-上海市","name":"上海市","normalizedName":"上海","province":"上海","lng":121.704685,"lat":31.386935},{"id":"shanghai-上海市","name":"上海市","normalizedName":"上海","province":"上海","lng":121.595494,"lat":31.431624},{"id":"shanghai-上海市","name":"上海市","normalizedName":"上海","province":"上海","lng":121.593993,"lat":31.203132},{"id":"shanghai-上海市","name":"上海市","normalizedName":"上海","province":"上海","lng":121.833474,"lat":31.34755},{"id":"shanghai-上海市","name":"上海市","normalizedName":"上海","province":"上海","lng":121.460004,"lat":31.238502},{"id":1,"name":"上饶市","normalizedName":"上饶","province":"江西","lng":117.260563,"lat":28.862648},{"id":2,"name":"韶关市","normalizedName":"韶关","province":"广东","lng":113.837083,"lat":24.835557},{"id":3,"name":"邵阳市","normalizedName":"邵阳","province":"湖南","lng":110.915052,"lat":26.899936},{"id":2,"name":"绍兴市","normalizedName":"绍兴","province":"浙江","lng":120.588589,"lat":29.706212},{"id":2,"name":"深圳市","normalizedName":"深圳","province":"广东","lng":114.208764,"lat":22.626282},{"id":3,"name":"神农架林区","normalizedName":"神农架林区","province":"湖北","lng":110.45958,"lat":31.581159},{"id":3,"name":"沈阳市","normalizedName":"沈阳","province":"辽宁","lng":123.104861,"lat":42.078214},{"id":4,"name":"嵊泗县","normalizedName":"嵊泗县","province":"浙江","lng":122.464375,"lat":30.710148},{"id":2,"name":"十堰市","normalizedName":"十堰","province":"湖北","lng":110.364131,"lat":32.459582},{"id":4,"name":"石河子市","normalizedName":"石河子","province":"新疆","lng":86.019641,"lat":44.248006},{"id":4,"name":"石家庄市","normalizedName":"石家庄","province":"河北","lng":114.438654,"lat":38.126902},{"id":"chongqing-石柱土家族自治县","name":"石柱土家族自治县","normalizedName":"石柱土家族自治县","province":"重庆","lng":108.283441,"lat":30.100926},{"id":"beijing-市区","name":"市区","normalizedName":"市区","province":"北京","lng":116.278445,"lat":39.964475},{"id":4,"name":"市辖区(南通市)","normalizedName":"市辖区(南通市)","province":"江苏","lng":121.103447,"lat":32.155646},{"id":2,"name":"市辖区(石嘴山市)","normalizedName":"市辖区(石嘴山市)","province":"宁夏","lng":106.509165,"lat":38.826519},{"id":"chongqing-双桥区","name":"双桥区","normalizedName":"双桥区","province":"重庆","lng":105.785384,"lat":29.499085},{"id":3,"name":"双鸭山市","normalizedName":"双鸭山","province":"黑龙江","lng":132.452864,"lat":46.590744},{"id":"beijing-顺义","name":"顺义","normalizedName":"顺义","province":"北京","lng":116.715223,"lat":40.157411},{"id":3,"name":"朔州市","normalizedName":"朔州","province":"陕西","lng":112.665062,"lat":39.622476},{"id":3,"name":"思茅市","normalizedName":"思茅","province":"云南","lng":100.757421,"lat":23.11684},{"id":1,"name":"四平市","normalizedName":"四平","province":"吉林","lng":124.547936,"lat":43.499264},{"id":"shanghai-松江区","name":"松江区","normalizedName":"松江区","province":"上海","lng":121.185148,"lat":31.005686},{"id":1,"name":"苏州市","normalizedName":"苏州","province":"江苏","lng":120.601231,"lat":31.37729},{"id":1,"name":"宿迁市","normalizedName":"宿迁","province":"江苏","lng":118.426843,"lat":33.591653},{"id":2,"name":"宿州市","normalizedName":"宿州","province":"安徽","lng":117.084902,"lat":33.931243},{"id":2,"name":"绥化市","normalizedName":"绥化","province":"黑龙江","lng":126.182189,"lat":46.693245},{"id":4,"name":"随州市","normalizedName":"随州","province":"湖北","lng":113.451633,"lat":31.848598},{"id":3,"name":"遂宁县","normalizedName":"遂宁县","province":"四川","lng":105.520518,"lat":30.621096},{"id":4,"name":"塔城市","normalizedName":"塔城","province":"新疆","lng":84.843463,"lat":45.520558},{"id":2,"name":"塔河县","normalizedName":"塔河县","province":"黑龙江","lng":124.294499,"lat":52.146592},{"id":1,"name":"台北市","normalizedName":"台北","province":"台湾","lng":121.519709,"lat":25.05672},{"id":4,"name":"台北县","normalizedName":"台北县","province":"台湾","lng":121.570652,"lat":25.028042},{"id":3,"name":"台东县","normalizedName":"台东县","province":"台湾","lng":121.066523,"lat":22.918046},{"id":1,"name":"台南市","normalizedName":"台南","province":"台湾","lng":120.164942,"lat":23.00089},{"id":3,"name":"台南县","normalizedName":"台南县","province":"台湾","lng":120.30847,"lat":23.192683},{"id":2,"name":"台中市","normalizedName":"台中","province":"台湾","lng":120.658513,"lat":24.175106},{"id":3,"name":"台中县","normalizedName":"台中县","province":"台湾","lng":120.857899,"lat":24.237914},{"id":4,"name":"台州市","normalizedName":"台州","province":"浙江","lng":121.203238,"lat":28.714451},{"id":4,"name":"太原市","normalizedName":"太原","province":"陕西","lng":112.368355,"lat":37.98701},{"id":4,"name":"泰安市","normalizedName":"泰安","province":"山东","lng":116.93026,"lat":35.989836},{"id":2,"name":"泰州市","normalizedName":"泰州","province":"江苏","lng":120.118371,"lat":32.327977},{"id":3,"name":"唐山市","normalizedName":"唐山","province":"河北","lng":118.364872,"lat":39.581241},{"id":3,"name":"桃园县","normalizedName":"桃园县","province":"台湾","lng":121.242383,"lat":24.866925},{"id":"tianjin-天津市","name":"天津市","normalizedName":"天津","province":"天津","lng":117.182328,"lat":39.253402},{"id":"tianjin-天津市","name":"天津市","normalizedName":"天津","province":"天津","lng":117.856399,"lat":39.248222},{"id":"tianjin-天津市","name":"天津市","normalizedName":"天津","province":"天津","lng":117.406528,"lat":39.12917},{"id":"tianjin-天津市","name":"天津市","normalizedName":"天津","province":"天津","lng":117.632412,"lat":38.997523},{"id":"tianjin-天津市","name":"天津市","normalizedName":"天津","province":"天津","lng":117.194551,"lat":39.134753},{"id":"tianjin-天津市","name":"天津市","normalizedName":"天津","province":"天津","lng":117.129811,"lat":39.027104},{"id":"tianjin-天津市","name":"天津市","normalizedName":"天津","province":"天津","lng":117.382431,"lat":38.969913},{"id":"tianjin-天津市","name":"天津市","normalizedName":"天津","province":"天津","lng":117.39725,"lat":38.754746},{"id":4,"name":"天门市","normalizedName":"天门","province":"湖北","lng":113.025884,"lat":30.603879},{"id":2,"name":"天水市","normalizedName":"天水","province":"甘肃","lng":105.699221,"lat":34.625575},{"id":2,"name":"天长市","normalizedName":"天长","province":"安徽","lng":118.954812,"lat":32.723106},{"id":2,"name":"铁岭市","normalizedName":"铁岭","province":"辽宁","lng":124.147475,"lat":42.651915},{"id":4,"name":"通化市","normalizedName":"通化","province":"吉林","lng":125.948108,"lat":41.910031},{"id":4,"name":"通辽市","normalizedName":"通辽","province":"内蒙古","lng":121.432541,"lat":43.858479},{"id":"beijing-通州","name":"通州","normalizedName":"通州","province":"北京","lng":116.719233,"lat":39.819941},{"id":1,"name":"同仁县","normalizedName":"同仁县","province":"青海","lng":101.616293,"lat":35.112339},{"id":4,"name":"铜川市","normalizedName":"铜川","province":"山西","lng":109.036673,"lat":35.19236},{"id":"chongqing-铜梁县","name":"铜梁县","normalizedName":"铜梁县","province":"重庆","lng":106.010027,"lat":29.820281},{"id":3,"name":"铜陵市","normalizedName":"铜陵","province":"安徽","lng":117.914122,"lat":30.958442},{"id":2,"name":"铜仁市","normalizedName":"铜仁","province":"贵州","lng":108.526448,"lat":28.020365},{"id":"chongqing-潼南县","name":"潼南县","normalizedName":"潼南县","province":"重庆","lng":105.799752,"lat":30.141755},{"id":"chongqing-万盛区","name":"万盛区","normalizedName":"万盛区","province":"重庆","lng":106.90543,"lat":28.911111},{"id":"chongqing-万州区","name":"万州区","normalizedName":"万州区","province":"重庆","lng":108.419494,"lat":30.705406},{"id":"chongqing-万州区","name":"万州区","normalizedName":"万州区","province":"重庆","lng":108.423372,"lat":30.759014},{"id":4,"name":"威海市","normalizedName":"威海","province":"山东","lng":122.050496,"lat":37.058636},{"id":3,"name":"潍坊市","normalizedName":"潍坊","province":"山东","lng":119.084522,"lat":36.485866},{"id":3,"name":"渭南市","normalizedName":"渭南","province":"山西","lng":109.830672,"lat":34.965615},{"id":3,"name":"温州市","normalizedName":"温州","province":"浙江","lng":120.494267,"lat":27.840498},{"id":2,"name":"文山县","normalizedName":"文山县","province":"云南","lng":104.712997,"lat":23.58344},{"id":2,"name":"乌兰浩特市","normalizedName":"乌兰浩特","province":"内蒙古","lng":121.495602,"lat":46.167637},{"id":4,"name":"乌兰县","normalizedName":"乌兰县","province":"青海","lng":95.571207,"lat":37.017},{"id":3,"name":"乌鲁木齐市","normalizedName":"乌鲁木齐","province":"新疆","lng":87.780147,"lat":43.508802},{"id":"chongqing-巫山县","name":"巫山县","normalizedName":"巫山县","province":"重庆","lng":109.905016,"lat":31.112407},{"id":"chongqing-巫溪县","name":"巫溪县","normalizedName":"巫溪县","province":"重庆","lng":109.417959,"lat":31.529791},{"id":4,"name":"烏海市","normalizedName":"烏海","province":"内蒙古","lng":106.85625,"lat":39.54914},{"id":3,"name":"无锡市","normalizedName":"无锡","province":"江苏","lng":120.24966,"lat":31.637038},{"id":2,"name":"吴忠市","normalizedName":"吴忠","province":"宁夏","lng":106.161316,"lat":37.390634},{"id":4,"name":"芜湖市","normalizedName":"芜湖","province":"安徽","lng":118.3058,"lat":31.056516},{"id":3,"name":"梧州市","normalizedName":"梧州","province":"广西","lng":110.992622,"lat":23.554577},{"id":2,"name":"武汉市","normalizedName":"武汉","province":"湖北","lng":114.353073,"lat":30.672626},{"id":"chongqing-武隆县","name":"武隆县","normalizedName":"武隆县","province":"重庆","lng":107.690404,"lat":29.37793},{"id":"tianjin-武清县","name":"武清县","normalizedName":"武清县","province":"天津","lng":117.013555,"lat":39.426016},{"id":2,"name":"武威市","normalizedName":"武威","province":"甘肃","lng":102.894074,"lat":37.717099},{"id":2,"name":"西安市","normalizedName":"西安","province":"山西","lng":108.807882,"lat":34.119471},{"id":1,"name":"西昌市","normalizedName":"西昌","province":"四川","lng":102.044521,"lat":27.962244},{"id":3,"name":"西峰市","normalizedName":"西峰","province":"甘肃","lng":107.465626,"lat":36.184761},{"id":2,"name":"西宁市","normalizedName":"西宁","province":"青海","lng":101.407085,"lat":36.863662},{"id":1,"name":"锡林浩特市","normalizedName":"锡林浩特","province":"内蒙古","lng":115.686776,"lat":44.079202},{"id":3,"name":"夏河县","normalizedName":"夏河县","province":"甘肃","lng":102.757319,"lat":34.146354},{"id":3,"name":"仙桃市","normalizedName":"仙桃","province":"湖北","lng":113.319836,"lat":30.323709},{"id":4,"name":"咸宁市","normalizedName":"咸宁","province":"湖北","lng":114.121452,"lat":29.590882},{"id":1,"name":"咸阳市","normalizedName":"咸阳","province":"山西","lng":108.392887,"lat":34.888241},{"id":1,"name":"香河县","normalizedName":"香河县","province":"河北","lng":116.999116,"lat":39.837293},{"id":4,"name":"湘潭市","normalizedName":"湘潭","province":"湖南","lng":112.556584,"lat":27.737614},{"id":1,"name":"襄樊市","normalizedName":"襄樊","province":"湖北","lng":111.872146,"lat":31.913051},{"id":1,"name":"孝感市","normalizedName":"孝感","province":"湖北","lng":113.902221,"lat":31.163433},{"id":2,"name":"忻州市","normalizedName":"忻州","province":"陕西","lng":112.33447,"lat":38.89},{"id":4,"name":"新乡市","normalizedName":"新乡","province":"河南","lng":114.10726,"lat":35.329415},{"id":2,"name":"新余市","normalizedName":"新余","province":"江西","lng":114.881618,"lat":27.821945},{"id":1,"name":"新竹县","normalizedName":"新竹县","province":"台湾","lng":121.090281,"lat":24.684483},{"id":2,"name":"信阳市","normalizedName":"信阳","province":"河南","lng":114.76171,"lat":32.1073},{"id":2,"name":"邢台市","normalizedName":"邢台","province":"河北","lng":114.811267,"lat":37.215884},{"id":3,"name":"兴化市","normalizedName":"兴化","province":"江苏","lng":119.951565,"lat":32.960586},{"id":1,"name":"兴义市","normalizedName":"兴义","province":"贵州","lng":105.454081,"lat":25.291899},{"id":"chongqing-秀山土家族苗族自治县","name":"秀山土家族苗族自治县","normalizedName":"秀山土家族苗族自治县","province":"重庆","lng":109.042525,"lat":28.52639},{"id":4,"name":"徐州市","normalizedName":"徐州","province":"江苏","lng":117.493051,"lat":34.331003},{"id":4,"name":"许昌市","normalizedName":"许昌","province":"河南","lng":113.717823,"lat":34.053239},{"id":3,"name":"宣州市","normalizedName":"宣州","province":"安徽","lng":118.81246,"lat":30.693388},{"id":2,"name":"雅安市","normalizedName":"雅安","province":"四川","lng":102.676526,"lat":29.878739},{"id":2,"name":"烟台市","normalizedName":"烟台","province":"山东","lng":120.813548,"lat":37.199781},{"id":2,"name":"延安市","normalizedName":"延安","province":"山西","lng":109.191195,"lat":36.557489},{"id":"beijing-延庆","name":"延庆","normalizedName":"延庆","province":"北京","lng":116.152461,"lat":40.539586},{"id":2,"name":"盐城市","normalizedName":"盐城","province":"江苏","lng":120.242191,"lat":33.46944},{"id":1,"name":"扬州市","normalizedName":"扬州","province":"江苏","lng":119.470308,"lat":32.734386},{"id":1,"name":"阳泉市","normalizedName":"阳泉","province":"陕西","lng":113.485711,"lat":38.060227},{"id":2,"name":"阳西县","normalizedName":"阳西县","province":"广东","lng":111.842743,"lat":21.907224},{"id":4,"name":"叶鲁番市","normalizedName":"叶鲁番","province":"新疆","lng":89.638935,"lat":42.436019},{"id":3,"name":"伊春市","normalizedName":"伊春","province":"黑龙江","lng":129.213525,"lat":47.885728},{"id":2,"name":"伊宁市","normalizedName":"伊宁","province":"新疆","lng":82.112893,"lat":43.432855},{"id":4,"name":"宜宾市","normalizedName":"宜宾","province":"四川","lng":104.494655,"lat":28.601539},{"id":2,"name":"宜昌市","normalizedName":"宜昌","province":"湖北","lng":111.148145,"lat":30.729278},{"id":1,"name":"宜春市","normalizedName":"宜春","province":"江西","lng":114.912883,"lat":28.241182},{"id":2,"name":"宜兰县","normalizedName":"宜兰县","province":"台湾","lng":121.649445,"lat":24.599859},{"id":2,"name":"宜兴市","normalizedName":"宜兴","province":"江苏","lng":119.814715,"lat":31.36084},{"id":1,"name":"益阳市","normalizedName":"益阳","province":"湖南","lng":112.01367,"lat":28.631576},{"id":4,"name":"银川市","normalizedName":"银川","province":"宁夏","lng":106.190999,"lat":38.525316},{"id":4,"name":"鹰潭市","normalizedName":"鹰潭","province":"江西","lng":117.094322,"lat":28.21107},{"id":4,"name":"营口市","normalizedName":"营口","province":"辽宁","lng":122.342208,"lat":40.425107},{"id":"chongqing-永川市","name":"永川市","normalizedName":"永川","province":"重庆","lng":105.838508,"lat":29.242508},{"id":2,"name":"永州市","normalizedName":"永州","province":"湖南","lng":111.721064,"lat":25.785247},{"id":"chongqing-酉阳土家族苗族自治县","name":"酉阳土家族苗族自治县","normalizedName":"酉阳土家族苗族自治县","province":"重庆","lng":108.783724,"lat":28.860271},{"id":"chongqing-渝北区","name":"渝北区","normalizedName":"渝北区","province":"重庆","lng":106.740437,"lat":29.827749},{"id":3,"name":"榆次市","normalizedName":"榆次","province":"陕西","lng":112.737961,"lat":37.241922},{"id":4,"name":"榆林市","normalizedName":"榆林","province":"山西","lng":109.300182,"lat":37.807846},{"id":1,"name":"玉环县","normalizedName":"玉环县","province":"浙江","lng":121.249984,"lat":28.152051},{"id":2,"name":"玉林市","normalizedName":"玉林","province":"广西","lng":110.243265,"lat":22.407297},{"id":4,"name":"玉溪市","normalizedName":"玉溪","province":"云南","lng":102.229251,"lat":24.213133},{"id":2,"name":"岳阳市","normalizedName":"岳阳","province":"湖南","lng":113.18562,"lat":29.101487},{"id":4,"name":"云浮市","normalizedName":"云浮","province":"广东","lng":111.74054,"lat":22.813957},{"id":2,"name":"云林县","normalizedName":"云林县","province":"台湾","lng":120.421574,"lat":23.671596},{"id":1,"name":"云龙县","normalizedName":"云龙县","province":"云南","lng":100.055284,"lat":25.684014},{"id":"chongqing-云阳县","name":"云阳县","normalizedName":"云阳县","province":"重庆","lng":108.85534,"lat":31.030084},{"id":2,"name":"运城市","normalizedName":"运城","province":"陕西","lng":111.153138,"lat":35.24091},{"id":1,"name":"枣庄市","normalizedName":"枣庄","province":"山东","lng":117.383198,"lat":34.918951},{"id":1,"name":"泽当","normalizedName":"泽当","province":"西藏","lng":92.186651,"lat":28.690903},{"id":4,"name":"湛江市","normalizedName":"湛江","province":"广东","lng":110.190071,"lat":21.091946},{"id":3,"name":"张家口市","normalizedName":"张家口","province":"河北","lng":115.052753,"lat":40.865012},{"id":3,"name":"张掖市","normalizedName":"张掖","province":"甘肃","lng":99.855013,"lat":38.880666},{"id":4,"name":"彰化县","normalizedName":"彰化县","province":"台湾","lng":120.482106,"lat":23.950611},{"id":1,"name":"漳州市","normalizedName":"漳州","province":"福建","lng":117.577721,"lat":24.260537},{"id":3,"name":"长春市","normalizedName":"长春","province":"吉林","lng":125.747611,"lat":44.30237},{"id":3,"name":"长沙市","normalizedName":"长沙","province":"湖南","lng":113.098008,"lat":28.183269},{"id":"chongqing-长寿县","name":"长寿县","normalizedName":"长寿县","province":"重庆","lng":107.144645,"lat":29.9767},{"id":2,"name":"长治市","normalizedName":"长治","province":"陕西","lng":112.878728,"lat":36.38225},{"id":3,"name":"昭通市","normalizedName":"昭通","province":"云南","lng":104.050613,"lat":27.651311},{"id":2,"name":"诏安县","normalizedName":"诏安县","province":"福建","lng":117.388212,"lat":23.671751},{"id":2,"name":"肇庆市","normalizedName":"肇庆","province":"广东","lng":112.112773,"lat":23.606912},{"id":3,"name":"镇江市","normalizedName":"镇江","province":"江苏","lng":119.488297,"lat":32.01664},{"id":1,"name":"郑州市","normalizedName":"郑州","province":"河南","lng":113.42003,"lat":34.586824},{"id":3,"name":"治多县","normalizedName":"治多县","province":"青海","lng":94.156059,"lat":34.227957},{"id":2,"name":"中甸县","normalizedName":"中甸县","province":"云南","lng":99.468758,"lat":27.943152},{"id":2,"name":"中山市","normalizedName":"中山","province":"广东","lng":113.365316,"lat":22.543827},{"id":"chongqing-忠县","name":"忠县","normalizedName":"忠县","province":"重庆","lng":107.936232,"lat":30.32647},{"id":2,"name":"舟山市","normalizedName":"舟山","province":"浙江","lng":122.124089,"lat":30.049611},{"id":2,"name":"周口市","normalizedName":"周口","province":"河南","lng":114.912436,"lat":33.730216},{"id":2,"name":"株州市","normalizedName":"株州","province":"湖南","lng":113.533552,"lat":27.109874},{"id":4,"name":"珠海市","normalizedName":"珠海","province":"广东","lng":113.522385,"lat":22.298811},{"id":4,"name":"驻马店市","normalizedName":"驻马店","province":"河南","lng":114.160152,"lat":32.874623},{"id":2,"name":"资阳市","normalizedName":"资阳","province":"四川","lng":104.990717,"lat":30.178476},{"id":4,"name":"淄博市","normalizedName":"淄博","province":"山东","lng":118.048186,"lat":36.589042},{"id":1,"name":"自贡市","normalizedName":"自贡","province":"四川","lng":104.669934,"lat":29.281213},{"id":4,"name":"遵义市","normalizedName":"遵义","province":"贵州","lng":106.987129,"lat":28.169098}]